dask_yarn/__init__.py
dask_yarn/_version.py
dask_yarn/cli.py
dask_yarn/config.py
dask_yarn/core.py
dask_yarn/yarn.yaml
dask_yarn/tests/__init__.py
dask_yarn/tests/conftest.py
dask_yarn/tests/test_cli.py
dask_yarn/tests/test_core.py
dask_yarn-0.9.dist-info/LICENSE.txt
dask_yarn-0.9.dist-info/METADATA
dask_yarn-0.9.dist-info/WHEEL
dask_yarn-0.9.dist-info/entry_points.txt
dask_yarn-0.9.dist-info/top_level.txt
dask_yarn-0.9.dist-info/RECORD
