Metadata-Version: 2.1
Name: dask-yarn
Version: 0.9
Summary: Deploy dask clusters on Apache YARN
Home-page: UNKNOWN
License: BSD
Platform: UNKNOWN
Requires-Python: >=3.7
Requires-Dist: dask (>=2021.1.0)
Requires-Dist: distributed (>=2021.1.0)
Requires-Dist: skein (>=0.8.0)
Requires-Dist: grpcio (>=1.14.0)
